simplepso/__init__.py
simplepso/logging.py
simplepso/pso.py
simplepso/tests/__init__.py
simplepso/tests/test_pso_construction.py
simplepso/tests/test_robertson.py
simplepso-2.2.3.dist-info/LICENSE.txt
simplepso-2.2.3.dist-info/METADATA
simplepso-2.2.3.dist-info/WHEEL
simplepso-2.2.3.dist-info/top_level.txt
simplepso-2.2.3.dist-info/RECORD
